gfx_perp_sdk/Slabs.py
gfx_perp_sdk/__init__.py
gfx_perp_sdk/perp.py
gfx_perp_sdk/product.py
gfx_perp_sdk/trader.py
gfx_perp_sdk/utils.py
gfx_perp_sdk/agnostic/EventQueue.py
gfx_perp_sdk/agnostic/Slabs.py
gfx_perp_sdk/agnostic/__init__.py
gfx_perp_sdk/constant_instructions/__init__.py
gfx_perp_sdk/constant_instructions/instructions.py
gfx_perp_sdk/constants/__init__.py
gfx_perp_sdk/constants/perps_constants.py
gfx_perp_sdk/instructions/__init__.py
gfx_perp_sdk/instructions/cancel_order.py
gfx_perp_sdk/instructions/choose_successor.py
gfx_perp_sdk/instructions/claim_authority.py
gfx_perp_sdk/instructions/clear_expired_orderbook.py
gfx_perp_sdk/instructions/close_trader_risk_group.py
gfx_perp_sdk/instructions/consume_orderbook_events.py
gfx_perp_sdk/instructions/deposit_funds.py
gfx_perp_sdk/instructions/initialize_combo.py
gfx_perp_sdk/instructions/initialize_market_product.py
gfx_perp_sdk/instructions/initialize_market_product_group.py
gfx_perp_sdk/instructions/initialize_trader_risk_group.py
gfx_perp_sdk/instructions/instruction_tag.py
gfx_perp_sdk/instructions/new_order.py
gfx_perp_sdk/instructions/remove_market_product.py
gfx_perp_sdk/instructions/sweep_fees.py
gfx_perp_sdk/instructions/transfer_full_position.py
gfx_perp_sdk/instructions/update_product_funding.py
gfx_perp_sdk/instructions/update_trader_funding.py
gfx_perp_sdk/instructions/withdraw_funds.py
gfx_perp_sdk/types/__init__.py
gfx_perp_sdk/types/account_tag.py
gfx_perp_sdk/types/action_status.py
gfx_perp_sdk/types/average_position.py
gfx_perp_sdk/types/base.py
gfx_perp_sdk/types/bitset.py
gfx_perp_sdk/types/call_back_info.py
gfx_perp_sdk/types/cancel_order_params.py
gfx_perp_sdk/types/clear_expired_orderbook_params.py
gfx_perp_sdk/types/combo.py
gfx_perp_sdk/types/consume_orderbook_events_params.py
gfx_perp_sdk/types/deposit_funds_params.py
gfx_perp_sdk/types/dex_error.py
gfx_perp_sdk/types/fractional.py
gfx_perp_sdk/types/health_info.py
gfx_perp_sdk/types/health_result.py
gfx_perp_sdk-0.0.20.dist-info/LICENSE
gfx_perp_sdk-0.0.20.dist-info/METADATA
gfx_perp_sdk-0.0.20.dist-info/WHEEL
gfx_perp_sdk-0.0.20.dist-info/top_level.txt
gfx_perp_sdk-0.0.20.dist-info/RECORD
