Metadata-Version: 2.1
Name: gfx_perp_sdk
Version: 0.0.20
Summary: Perp python sdk
Home-page: https://github.com/GooseFX1/gfx-perps-python-sdk
Author: Shashank Shekhar
Author-email: shashank@goosefx.io
License-File: LICENSE
Requires-Dist: pytest
